sphinx_diagrams/__init__.py
sphinx_diagrams/sphinx_diagrams.py
sphinx_diagrams-0.4.0.dist-info/LICENSE
sphinx_diagrams-0.4.0.dist-info/WHEEL
sphinx_diagrams-0.4.0.dist-info/METADATA
sphinx_diagrams-0.4.0.dist-info/RECORD
