Metadata-Version: 2.1
Name: sphinx-diagrams
Version: 0.4.0
Summary: Rendering Diagrams in Sphinx
Home-page: https://github.com/j-martin/sphinx-diagrams
License: BSD-2
Author: Jean-Martin Archer
Author-email: jm@jmartin.ca
Requires-Python: >=3.6,<4.0
Classifier: License :: Other/Proprietary License
Classifier: Programming Language :: Python :: 3
Classifier: Programming Language :: Python :: 3.6
Classifier: Programming Language :: Python :: 3.7
Classifier: Programming Language :: Python :: 3.8
Classifier: Programming Language :: Python :: 3.9
Requires-Dist: diagrams (>=0.16.0)
Project-URL: Repository, https://github.com/j-martin/sphinx-diagrams
